ecoscope/__init__.py
ecoscope/version.py
ecoscope/analysis/__init__.py
ecoscope/analysis/astronomy.py
ecoscope/analysis/classifier.py
ecoscope/analysis/ecograph.py
ecoscope/analysis/feature_density.py
ecoscope/analysis/geofence.py
ecoscope/analysis/geospatial.py
ecoscope/analysis/immobility.py
ecoscope/analysis/percentile.py
ecoscope/analysis/proximity.py
ecoscope/analysis/seasons.py
ecoscope/analysis/speed.py
ecoscope/analysis/UD/__init__.py
ecoscope/analysis/UD/etd_range.py
ecoscope/base/__init__.py
ecoscope/base/_dataclasses.py
ecoscope/base/base.py
ecoscope/base/utils.py
ecoscope/contrib/__init__.py
ecoscope/contrib/basemaps.py
ecoscope/contrib/foliumap.py
ecoscope/contrib/geemap.py
ecoscope/contrib/legend.txt
ecoscope/io/__init__.py
ecoscope/io/earthranger.py
ecoscope/io/eetools.py
ecoscope/io/raster.py
ecoscope/io/utils.py
ecoscope/mapping/__init__.py
ecoscope/mapping/map.py
ecoscope/plotting/__init__.py
ecoscope/plotting/plot.py
ecoscope-1.7.3.dist-info/LICENSE
ecoscope-1.7.3.dist-info/METADATA
ecoscope-1.7.3.dist-info/WHEEL
ecoscope-1.7.3.dist-info/top_level.txt
ecoscope-1.7.3.dist-info/RECORD
