Metadata-Version: 2.1
Name: ecoscope
Version: 1.7.3
Summary: Standard Analytical Reporting Framework for Conservation
Home-page: http://github.com/wildlife-dynamics/ecoscope
Author: Jake Wall
Author-email: walljcg@gmail.com
License: MIT
Platform: Posix; MacOS X; Windows
Classifier: License :: OSI Approved :: BSD License
Classifier: Programming Language :: Python
Classifier: Programming Language :: Python :: 3
Classifier: Programming Language :: Python :: 3.4
Classifier: Programming Language :: Python :: 3.5
Classifier: Programming Language :: Python :: 3.6
Classifier: Programming Language :: Python :: 3.7
Classifier: Programming Language :: Python :: 3.8
Classifier: Programming Language :: Python :: 3.9
Classifier: Programming Language :: Python :: 3.10
License-File: LICENSE
Requires-Dist: affine
Requires-Dist: astroplan
Requires-Dist: backoff
Requires-Dist: datashader
Requires-Dist: earthengine-api
Requires-Dist: earthranger-client
Requires-Dist: folium
Requires-Dist: geopandas <=0.14.2
Requires-Dist: igraph
Requires-Dist: ipywidgets
Requires-Dist: kaleido
Requires-Dist: mapclassify
Requires-Dist: matplotlib
Requires-Dist: networkx
Requires-Dist: numba
Requires-Dist: plotly
Requires-Dist: pyarrow
Requires-Dist: pyproj
Requires-Dist: pytest
Requires-Dist: pytest-cov
Requires-Dist: pytest-mock
Requires-Dist: pytest-reportlog
Requires-Dist: rasterio
Requires-Dist: scipy
Requires-Dist: scikit-image
Requires-Dist: scikit-learn
Requires-Dist: selenium
Requires-Dist: tqdm
Requires-Dist: xyzservices
